MANIFEST.in
README.md
requirements.txt
setup.cfg
setup.py
covid_daily/__init__.py
covid_daily/constants.py
covid_daily/covid.py
covid_daily/regex.py
covid_daily/utils.py
covid_daily.egg-info/PKG-INFO
covid_daily.egg-info/SOURCES.txt
covid_daily.egg-info/dependency_links.txt
covid_daily.egg-info/requires.txt
covid_daily.egg-info/top_level.txt
docs/requirements.txt
tests/__init__.py
tests/requirements.txt
tests/test_covid_daily.py