Metadata-Version: 2.1
Name: covid-daily
Version: 1.3.0
Summary: Coronavirus (COVID-19) Daily Data from Worldometers with Python
Home-page: https://www.github.com/alvarobartt/covid-daily
Author: Alvaro Bartolome del Canto
Author-email: alvarob96@usal.es
License: MIT License
Download-URL: https://github.com/alvarobartt/covid-daily/archive/1.3.0.tar.gz
Project-URL: Bug Reports, https://github.com/alvarobartt/covid-daily/issues
Project-URL: Source, https://github.com/alvarobartt/covid-daily
Project-URL: Documentation, https://covid_daily.readthedocs.io/
Platform: UNKNOWN
Classifier: Development Status :: 4 - Beta
Classifier: Programming Language :: Python :: 3 :: Only
Classifier: Programming Language :: Python :: 3.6
Classifier: Programming Language :: Python :: 3.7
Classifier: Programming Language :: Python :: 3.8
Classifier: Programming Language :: Python :: 3.9
Classifier: License :: OSI Approved :: MIT License
Classifier: Intended Audience :: Developers
Classifier: Topic :: Software Development :: Libraries
Requires-Python: >=3
Provides-Extra: docs
Provides-Extra: tests
